LICENSE.txt
README.md
setup.cfg
setup.py
django_dropbox_storage/__init__.py
django_dropbox_storage/models.py
django_dropbox_storage/settings.py
django_dropbox_storage/storage.py
django_dropbox_storage/tests.py
django_dropbox_storage/views.py
django_dropbox_storage/management/__init__.py
django_dropbox_storage/management/commands/__init__.py
django_dropbox_storage/management/commands/get_dropbox_token.py
django_dropbox_storage_fixed.egg-info/PKG-INFO
django_dropbox_storage_fixed.egg-info/SOURCES.txt
django_dropbox_storage_fixed.egg-info/dependency_links.txt
django_dropbox_storage_fixed.egg-info/requires.txt
django_dropbox_storage_fixed.egg-info/top_level.txt