Metadata-Version: 2.1
Name: django-dropbox-storage-fixed
Version: 0.5.1
Summary: A Dropbox Storage for your Django apps
Home-page: https://github.com/Liqudity2provider/django-dropbox-storage-fixed
Author: Emanuele Bertoldi
Author-email: emanuele.bertoldi@gmail.com
License: MIT
Download-URL: https://github.com/Liqudity2provider/django-dropbox-storage-fixed/archive/refs/tags/v0.5.1.tar.gz
Keywords: django storage dropbox fixed
Platform: UNKNOWN
